<?xml version="1.0" encoding="utf-8" ?>
<Themes>
  <Theme Name="default" Title="Default"></Theme>
  <Theme Name="cerulean" Title="Cerulean"></Theme>
  <Theme Name="cosmo" Title="Cosmo"></Theme>
  <Theme Name="cyborg" Title="Cyborg"></Theme>
  <Theme Name="darkly" Title="Darkly"></Theme>
  <Theme Name="flatly" Title="Flatly"></Theme>
  <Theme Name="journal" Title="Journal"></Theme>
  <Theme Name="lumen" Title="Lumen"></Theme>
  <Theme Name="paper" Title="Paper"></Theme>
  <Theme Name="readable" Title="Readable"></Theme>
  <Theme Name="sandstone" Title="Sandstone"></Theme>
  <Theme Name="simplex" Title="Simplex"></Theme>
  <Theme Name="slate" Title="Slate"></Theme>
  <Theme Name="spacelab" Title="Spacelab"></Theme>
  <Theme Name="superhero" Title="Superhero"></Theme>
  <Theme Name="united" Title="United"></Theme>
  <Theme Name="yeti" Title="Yeti"></Theme>

  <Theme4 Name="default" Title="Default"></Theme4>
  <Theme4 Name="dx" Title="DevExpress Themes" IsGroup="true"></Theme4>
  <Theme4 Name="dx/purple" Title="Purple"></Theme4>
  <Theme4 Name="dx/office-white" Title="Office White"></Theme4>
  <Theme4 Name="bootswatch" Title="Bootswatch Themes" IsGroup="true"></Theme4>
  <Theme4 Name="bootswatch/cerulean" Title="Cerulean"></Theme4>
  <Theme4 Name="bootswatch/cosmo" Title="Cosmo"></Theme4>
  <Theme4 Name="bootswatch/cyborg" Title="Cyborg"></Theme4>
  <Theme4 Name="bootswatch/darkly" Title="Darkly"></Theme4>
  <Theme4 Name="bootswatch/flatly" Title="Flatly"></Theme4>
  <Theme4 Name="bootswatch/journal" Title="Journal"></Theme4>
  <Theme4 Name="bootswatch/litera" Title="Litera"></Theme4>
  <Theme4 Name="bootswatch/lumen" Title="Lumen"></Theme4>
  <Theme4 Name="bootswatch/lux" Title="Lux"></Theme4>
  <Theme4 Name="bootswatch/materia" Title="Materia"></Theme4>
  <Theme4 Name="bootswatch/minty" Title="Minty"></Theme4>
  <Theme4 Name="bootswatch/pulse" Title="Pulse"></Theme4>
  <Theme4 Name="bootswatch/sandstone" Title="Sandstone"></Theme4>
  <Theme4 Name="bootswatch/simplex" Title="Simplex"></Theme4>
  <Theme4 Name="bootswatch/sketchy" Title="Sketchy"></Theme4>
  <Theme4 Name="bootswatch/slate" Title="Slate"></Theme4>
  <Theme4 Name="bootswatch/solar" Title="Solar"></Theme4>
  <Theme4 Name="bootswatch/spacelab" Title="Spacelab"></Theme4>
  <Theme4 Name="bootswatch/superhero" Title="Superhero"></Theme4>
  <Theme4 Name="bootswatch/united" Title="United"></Theme4>
  <Theme4 Name="bootswatch/yeti" Title="Yeti"></Theme4>
</Themes>